pypofatu/__init__.py
pypofatu/__main__.py
pypofatu/dataset.py
pypofatu/errata.py
pypofatu/metadata.json
pypofatu/models.py
pypofatu/util.py
pypofatu/commands/__init__.py
pypofatu/commands/check.py
pypofatu/commands/dist.py
pypofatu/commands/dump.py
pypofatu/commands/paramstats.py
pypofatu/commands/query.py
pypofatu-1.6.0.dist-info/LICENSE
pypofatu-1.6.0.dist-info/METADATA
pypofatu-1.6.0.dist-info/WHEEL
pypofatu-1.6.0.dist-info/entry_points.txt
pypofatu-1.6.0.dist-info/top_level.txt
pypofatu-1.6.0.dist-info/RECORD
