Metadata-Version: 2.1
Name: pypofatu
Version: 1.6.0
Summary: programmatic access to pofatu-data
Home-page: https://github.com/pofatu/pypofatu
Author: Robert Forkel
Author-email: robert_forkel@eva.mpg.de
License: Apache 2.0
Keywords: data
Platform: any
Classifier: Development Status :: 5 - Production/Stable
Classifier: Intended Audience :: Developers
Classifier: Intended Audience :: Science/Research
Classifier: Natural Language :: English
Classifier: Operating System :: OS Independent
Classifier: Environment :: Console
Classifier: License :: OSI Approved :: Apache Software License
Classifier: Topic :: Scientific/Engineering
Classifier: Topic :: Scientific/Engineering :: Bio-Informatics
Classifier: Topic :: Software Development :: Libraries :: Python Modules
Classifier: Programming Language :: Python :: 3
Classifier: Programming Language :: Python :: 3.8
Classifier: Programming Language :: Python :: 3.9
Classifier: Programming Language :: Python :: 3.10
Classifier: Programming Language :: Python :: 3.11
Classifier: Programming Language :: Python :: Implementation :: CPython
Classifier: Programming Language :: Python :: Implementation :: PyPy
Classifier: License :: OSI Approved :: BSD License
Requires-Python: >=3.8
License-File: LICENSE
Requires-Dist: csvw
Requires-Dist: pybtex
Requires-Dist: attrs (>=19.3)
Requires-Dist: xlrd (<2)
Requires-Dist: clldutils (>=3.5)
Requires-Dist: tqdm
Provides-Extra: dev
Requires-Dist: tox ; extra == 'dev'
Requires-Dist: flake8 ; extra == 'dev'
Requires-Dist: wheel (>=0.36) ; extra == 'dev'
Requires-Dist: twine ; extra == 'dev'
Requires-Dist: build ; extra == 'dev'
Provides-Extra: test
Requires-Dist: pytest (>=5) ; extra == 'test'
Requires-Dist: pytest-mock ; extra == 'test'
Requires-Dist: pytest-cov ; extra == 'test'
Requires-Dist: coverage (>=4.2) ; extra == 'test'
